pymszip/__init__.py
pymszip-1.0.1.dist-info/WHEEL
pymszip-1.0.1.dist-info/METADATA
pymszip-1.0.1.dist-info/RECORD
