Metadata-Version: 2.1
Name: pymszip
Version: 1.0.1
Summary: Compress and Decompress MSZIP data
Author-email: Frederik Reiter <pymszip@frereit.de>
Requires-Python: >=3.9.1
Classifier: Development Status :: 5 - Production/Stable
Classifier: Intended Audience :: Information Technology
Classifier: License :: OSI Approved :: MIT License
Classifier: Programming Language :: Python :: 3 :: Only
Classifier: Programming Language :: Python :: 3.9
Classifier: Programming Language :: Python :: 3.10
Classifier: Programming Language :: Python :: 3.11
Classifier: Programming Language :: Python :: 3.12
Requires-Dist: black~=24.4.2 ; extra == "dev"
Requires-Dist: pytest ; extra == "dev"
Provides-Extra: dev
